alchemy/satest.py
postgresql_access/__init__.py
postgresql_access/certificatedatabase.py
postgresql_access/database.py
postgresql_access/main.py
postgresql_access-2.0.2.dist-info/licenses/LICENSE
tests/atest.py
tests/grouptest.py
postgresql_access-2.0.2.dist-info/METADATA
postgresql_access-2.0.2.dist-info/WHEEL
postgresql_access-2.0.2.dist-info/entry_points.txt
postgresql_access-2.0.2.dist-info/top_level.txt
postgresql_access-2.0.2.dist-info/RECORD
