Metadata-Version: 2.4
Name: postgresql_access
Version: 2.0.2
Author-email: Gerard <gweatherby@uchc.edu>
License: MIT
Requires-Python: >=3.8
License-File: LICENSE
Requires-Dist: keyring
Provides-Extra: psycopg2
Requires-Dist: psycopg2-binary; extra == "psycopg2"
Provides-Extra: psycopg3
Requires-Dist: psycopg[binary]; extra == "psycopg3"
Provides-Extra: alchemy
Requires-Dist: sqlalchemy; extra == "alchemy"
Dynamic: license-file
